flextag/__init__.py
flextag/flextag.py
flextag-0.3.0.dist-info/LICENSE
flextag-0.3.0.dist-info/METADATA
flextag-0.3.0.dist-info/WHEEL
flextag-0.3.0.dist-info/RECORD
