Metadata-Version: 2.3
Name: flextag
Version: 0.3.0
Summary: A lightweight markup language for structured content with powerful section-based organization, metadata filtering, and validation capabilities.
License: MIT
Author: DarrenHaba
Author-email: darrenhaba@live.com
Requires-Python: >=3.10,<3.13
Classifier: License :: OSI Approved :: MIT License
Classifier: Programming Language :: Python :: 3
Classifier: Programming Language :: Python :: 3.10
Classifier: Programming Language :: Python :: 3.11
Classifier: Programming Language :: Python :: 3.12
Requires-Dist: duckdb (>=1.1.3,<2.0.0)
Requires-Dist: ftml (>=0.1.0a1,<0.2.0)
Requires-Dist: numpy (>=2.1.3,<3.0.0)
Requires-Dist: pytest-cov (>=6.0.0,<7.0.0)
Requires-Dist: pyyaml (>=6.0.2,<7.0.0)
Requires-Dist: tomli (>=2.1.0,<3.0.0)
Requires-Dist: tomli-w (>=1.1.0,<2.0.0)
Project-URL: Bug Tracker, https://github.com/yourusername/flextag/issues
Project-URL: Homepage, https://github.com/yourusername/flextag
Project-URL: Repository, https://github.com/yourusername/flextag
